hdl/dither.sv
module dither (
  input wire clk_in,
  input wire rst_in,
  input wire a_valid,
  input wire [10:0] a_hcount,
  input wire [9:0] a_vcount,
  input wire [7:0] b,
  input wire [7:0] e,

  output logic dithered_pixel,
  output logic [10:0] dithered_hcount,
  output logic [9:0] dithered_vcount,
  output logic dithered_valid,

  output logic [7:0] updated_pixel,

  input wire [3:0] threshold_in
  );

  logic [8:0] a;
  logic [8:0] c;
  logic [8:0] d;
  logic [8:0] dithered_value;
  logic signed [7:0] quant_error;
  logic signed [11:0] new_b;
  logic signed [11:0] new_c;
  logic signed [11:0] new_d;
  logic signed [11:0] new_e;
  logic [7:0] threshold;

  assign threshold = threshold_in * 16;
  assign dithered_value = (a > threshold) ? 255 : 0; // dithered_value is either 255 or 0
  assign quant_error = a - dithered_value; // quant_error is -127 to 127
  
  assign new_b = ($signed(b) + ($signed(quant_error * $signed(7)) >>> 4));
  assign new_c = ($signed(c) + ($signed(quant_error * $signed(3)) >>> 4));
  assign new_d = ($signed(d) + ($signed(quant_error * $signed(5)) >>> 4));
  assign new_e = ($signed(e) + (quant_error >>> 4));

  always_ff @(posedge clk_in) begin
    if (rst_in)begin
      a <= 0;
      c <= 0;
      d <= 0;
      dithered_pixel <= 0;
      dithered_hcount <= 0;
      dithered_vcount <= 0;
      dithered_valid <= 0;
      updated_pixel <= 0;
    end else begin
        dithered_pixel <= (a > threshold) ? 0 : 1;
        a <= (new_b > 255) ? 255 : (new_b < 0) ? 0 : new_b;
        c <= (new_d > 255) ? 255 : (new_d < 0) ? 0 : new_d;
        d <= (new_e > 255) ? 255 : (new_e < 0) ? 0 : new_e;
        updated_pixel <= (new_c > 255) ? 255 : (new_c < 0) ? 0 : new_c;

        dithered_hcount <= a_hcount;
        dithered_vcount <= a_vcount;
        dithered_valid <= a_valid;
    end
  end
endmodule

sim/dither_tb.sv
`timescale 1ns / 1ps
`default_nettype none

module dither_tb();

  logic clk_in;
  logic rst_in;
  logic a_valid;
  logic [10:0] a_hcount;
  logic [9:0] a_vcount;
  logic [7:0] b;
  logic [7:0] e;

  logic dithered_pixel;
  logic [10:0] dithered_hcount;
  logic [9:0] dithered_vcount;
  logic dithered_valid;

  logic [7:0] updated_pixel;
  logic [3:0] threshold;

  dither dither_m (
    .clk_in(clk_in),
    .rst_in(rst_in),

    .a_valid(a_valid),
    .a_hcount(a_hcount),
    .a_vcount(a_vcount),
    .b(b),
    .e(e),

    .dithered_pixel(dithered_pixel),
    .dithered_hcount(dithered_hcount),
    .dithered_vcount(dithered_vcount),
    .dithered_valid(dithered_valid),
    .updated_pixel(updated_pixel),
    .threshold_in(threshold)
  );

  always begin
      #5;  //every 5 ns switch...so period of clock is 10 ns...100 MHz clock
      clk_in = !clk_in;
  end
  
  //initial block...this is our test simulation
  initial begin
    $dumpfile("dither_tb.vcd"); //file to store value change dump (vcd)
    $dumpvars(0,dither_tb);
    $display("Starting Sim"); //print nice message at start
    clk_in = 0;
    rst_in = 0;
    #10;
    rst_in = 1;
    #10;
    rst_in = 0;

    a_valid = 1;
    a_hcount = 1;
    a_vcount = 1;
    threshold = 8;
    
    for (int i = 0; i < 8; i++) begin
      b = 100;
      e = 100;
      #10;
      $display(dithered_pixel);
    end

    // for (int i = 0; i < 2; i++) begin
    //   b = 246;
    //   e = 75;
    //   #10;
    //   $display(dithered_pixel);
    //   b = 157;
    //   e = 120;
    //   #10;
    //   $display(dithered_pixel);
    //   b = 205;
    //   e = 176;
    //   #10;
    //   $display(dithered_pixel);
    // end
    
    $display("Simulation finished");
    $finish;
  end
endmodule
`default_nettype wire

dither_tb.vcd
$date
	Wed Nov 15 17:06:51 2023
$end
$version
	Icarus Verilog
$end
$timescale
	1ps
$end
$scope module dither_tb $end
$var wire 8 ! updated_pixel [7:0] $end
$var wire 10 " dithered_vcount [9:0] $end
$var wire 1 # dithered_valid $end
$var wire 1 $ dithered_pixel $end
$var wire 11 % dithered_hcount [10:0] $end
$var reg 11 & a_hcount [10:0] $end
$var reg 1 ' a_valid $end
$var reg 10 ( a_vcount [9:0] $end
$var reg 8 ) b [7:0] $end
$var reg 1 * clk_in $end
$var reg 8 + e [7:0] $end
$var reg 1 , rst_in $end
$var reg 4 - threshold [3:0] $end
$scope module dither_m $end
$var wire 11 . a_hcount [10:0] $end
$var wire 1 ' a_valid $end
$var wire 10 / a_vcount [9:0] $end
$var wire 8 0 b [7:0] $end
$var wire 1 * clk_in $end
$var wire 8 1 e [7:0] $end
$var wire 1 , rst_in $end
$var wire 4 2 threshold_in [3:0] $end
$var wire 8 3 threshold [7:0] $end
$var wire 8 4 quant_error [7:0] $end
$var wire 12 5 new_e [11:0] $end
$var wire 12 6 new_d [11:0] $end
$var wire 12 7 new_c [11:0] $end
$var wire 12 8 new_b [11:0] $end
$var wire 9 9 dithered_value [8:0] $end
$var reg 9 : a [8:0] $end
$var reg 9 ; c [8:0] $end
$var reg 9 < d [8:0] $end
$var reg 11 = dithered_hcount [10:0] $end
$var reg 1 $ dithered_pixel $end
$var reg 1 # dithered_valid $end
$var reg 10 > dithered_vcount [9:0] $end
$var reg 8 ? updated_pixel [7:0] $end
$upscope $end
$scope begin $ivl_for_loop0 $end
$var integer 32 @ i [31:0] $end
$upscope $end
$upscope $end
$enddefinitions $end
$comment Show the parameter values. $end
$dumpall
$end
#0
$dumpvars
b0 @
bx ?
bx >
bx =
bx <
bx ;
bx :
b0xxxxxxxx 9
bx 8
bx 7
bx 6
bx 5
bx 4
bx 3
bx 2
bx 1
bx 0
bx /
bx .
bx -
0,
bx +
0*
bx )
bx (
x'
bx &
bx %
x$
x#
bx "
bx !
$end
#5000
1*
#10000
0*
1,
#15000
b0 !
b0 ?
0#
b0 "
b0 >
b0 %
b0 =
0$
b0 <
b0 ;
b0 :
1*
#20000
b1100100 8
b0 7
b0 6
b1100100 5
b0 4
b0 9
0*
b1100100 +
b1100100 1
b1100100 )
b1100100 0
b10000000 3
b1000 -
b1000 2
b1 (
b1 /
b1 &
b1 .
1'
0,
#25000
b10001111 8
b10010 7
b1101010 5
b10000011 6
b1100100 4
1#
b1 "
b1 >
b1 %
b1 =
b1100100 <
b1100100 :
1$
1*
#30000
0*
b1 @
#35000
b110011 8
b1011101 5
b1000111 6
b1101110 7
b11111111 9
b10010000 4
b10010 !
b10010 ?
b1101010 <
b10000011 ;
b10001111 :
1*
#40000
0*
b10 @
#45000
b1111010 8
b1100111 5
b1101100 6
b1010000 7
b0 9
b110011 4
b1101110 !
b1101110 ?
b1011101 <
b1000111 ;
b110011 :
0$
1*
#50000
0*
b11 @
#55000
b10011001 8
b1101011 5
b10001101 6
b10000010 7
b1111010 4
b1010000 !
b1010000 ?
b1100111 <
b1101100 ;
b1111010 :
1$
1*
#60000
0*
b100 @
#65000
b110111 8
b1011101 5
b1001011 6
b1111001 7
b11111111 9
b10011010 4
b10000010 !
b10000010 ?
b1101011 <
b10001101 ;
b10011001 :
1*
#70000
0*
b101 @
#75000
b1111100 8
b1100111 5
b1101110 6
b1010101 7
b0 9
b110111 4
b1111001 !
b1111001 ?
b1011101 <
b1001011 ;
b110111 :
0$
1*
#80000
0*
b110 @
#85000
b10011010 8
b1101011 5
b10001101 6
b10000101 7
b1111100 4
b1010101 !
b1010101 ?
b1100111 <
b1101110 ;
b1111100 :
1$
1*
#90000
0*
b111 @
#95000
b110111 8
b1011101 5
b1001011 6
b1111010 7
b11111111 9
b10011011 4
b10000101 !
b10000101 ?
b1101011 <
b10001101 ;
b10011010 :
1*
#100000
0*
b1000 @
